labext/__init__.py
labext/module.py
labext/prelude.py
labext/widget.py
labext/apps/__init__.py
labext/apps/slider.py
labext/apps/annotators/__init__.py
labext/apps/annotators/base_annotator.py
labext/apps/annotators/batch_classification_annotator.py
labext/apps/annotators/classification_annotator.py
labext/apps/annotators/persistent_annotator.py
labext/modules/__init__.py
labext/modules/data_table.py
labext/modules/jquery.py
labext/modules/lab_ext.py
labext/modules/selectize.py
labext/modules/tippy.py
labext/widgets/__init__.py
labext/widgets/button.py
labext/widgets/hideable_button.py
labext/widgets/html.py
labext/widgets/icon.py
labext/widgets/output.py
labext/widgets/selection.py
labext-3.0.0.dist-info/METADATA
labext-3.0.0.dist-info/WHEEL
labext-3.0.0.dist-info/top_level.txt
labext-3.0.0.dist-info/RECORD
