Metadata-Version: 2.1
Name: labext
Version: 3.0.0
Summary: Extra widgets for Jupyter Lab
Home-page: https://github.com/binh-vu/labext
Author: Binh Vu
Author-email: binh@toan2.com
License: MIT
Platform: UNKNOWN
Requires-Python: >3.6
Requires-Dist: ipywidgets
Requires-Dist: IPython
Requires-Dist: jupyter-core
Requires-Dist: requests
Requires-Dist: ipyevents
Requires-Dist: ipycallback
Requires-Dist: ujson
